Workbook

Sheet Board
A1: Brightline Logistics - In-Cab Model Trade-off Board
A2: Scanned bills of lading + spoken driver notes, one 16-class model. Every figure is the mean of repeated benchmark trials (see Protocol).
A3: =IF(COUNTA(Runs!$A:$A)<2,"Measured on: (no runs yet)","Measured on: "&INDEX(Runs!$W:$W,2)&" | torch "&INDEX(Runs!$X:$X,2))
A4: Legend: blue = input you can change | yellow fill = decision cells to fill in | green = pulled from another sheet | black = formula
A6: Tablet budget (edit to match the agreed hardware target)
A7: Accuracy floor (overall) | B7: 0.85
A8: p95 latency ceiling (ms, measured GPU) | B8: 10
A9: Shipped model size ceiling (MB) | B9: 8
A11: Config | B11: Run ID | C11: Variant | D11: What changed | E11: Trials | F11: Accuracy | G11: Docs acc | H11: Notes acc | I11: p50 ms | J11: p95 ms | K11: p50 spread across trials (ms) | L11: Peak GPU mem (MB) | M11: Shipped size (MB) | N11: Params | O11: Accuracy vs baseline (pts) | P11: p95 speed-up vs baseline (x) | Q11: Size reduction vs baseline (x) | R11: Meets budget? | S11: Rank | T11: Verdict
A12: baseline | B12: eecf0fdd | C12: baseline | D12: 4-layer softmax-attention transformer, FP32 | E12: =IF($B12="","",COUNTIFS(Runs!$A$2:$A$21,$B12)) | F12: =IFERROR(AVERAGEIFS(Runs!$I$2:$I$21,Runs!$A$2:$A$21,$B12),"") | G12: =IFERROR(AVERAGEIFS(Runs!$J$2:$J$21,Runs!$A$2:$A$21,$B12),"") | H12: =IFERROR(AVERAGEIFS(Runs!$K$2:$K$21,Runs!$A$2:$A$21,$B12),"") | I12: =IFERROR(AVERAGEIFS(Runs!$L$2:$L$21,Runs!$A$2:$A$21,$B12),"") | J12: =IFERROR(AVERAGEIFS(Runs!$M$2:$M$21,Runs!$A$2:$A$21,$B12),"") | K12: =IFERROR(IF(E12="","",_xlfn.MAXIFS(Runs!$L$2:$L$21,Runs!$A$2:$A$21,$B12)-_xlfn.MINIFS(Runs!$L$2:$L$21,Runs!$A$2:$A$21,$B12)),"") | L12: =IFERROR(AVERAGEIFS(Runs!$Q$2:$Q$21,Runs!$A$2:$A$21,$B12),"") | M12: =IFERROR(AVERAGEIFS(Runs!$U$2:$U$21,Runs!$A$2:$A$21,$B12),"") | N12: =IFERROR(AVERAGEIFS(Runs!$S$2:$S$21,Runs!$A$2:$A$21,$B12),"") | O12: =IFERROR((F12-F$12)*100,"") | P12: =IFERROR(J$12/J12,"") | Q12: =IFERROR(M$12/M12,"") | R12: =IF(F12="","",IF(AND(F12>=$B$7,J12<=$B$8,M12<=$B$9),"PASS","FAIL"))
A13: linear_attention | B13: 1610f4f4 | C13: architecture | D13: Architecture variant: same 4-layer model, linear (elu+1) attention, FP32 | E13: =IF($B13="","",COUNTIFS(Runs!$A$2:$A$21,$B13)) | F13: =IFERROR(AVERAGEIFS(Runs!$I$2:$I$21,Runs!$A$2:$A$21,$B13),"") | G13: =IFERROR(AVERAGEIFS(Runs!$J$2:$J$21,Runs!$A$2:$A$21,$B13),"") | H13: =IFERROR(AVERAGEIFS(Runs!$K$2:$K$21,Runs!$A$2:$A$21,$B13),"") | I13: =IFERROR(AVERAGEIFS(Runs!$L$2:$L$21,Runs!$A$2:$A$21,$B13),"") | J13: =IFERROR(AVERAGEIFS(Runs!$M$2:$M$21,Runs!$A$2:$A$21,$B13),"") | K13: =IFERROR(IF(E13="","",_xlfn.MAXIFS(Runs!$L$2:$L$21,Runs!$A$2:$A$21,$B13)-_xlfn.MINIFS(Runs!$L$2:$L$21,Runs!$A$2:$A$21,$B13)),"") | L13: =IFERROR(AVERAGEIFS(Runs!$Q$2:$Q$21,Runs!$A$2:$A$21,$B13),"") | M13: =IFERROR(AVERAGEIFS(Runs!$U$2:$U$21,Runs!$A$2:$A$21,$B13),"") | N13: =IFERROR(AVERAGEIFS(Runs!$S$2:$S$21,Runs!$A$2:$A$21,$B13),"") | O13: =IFERROR((F13-F$12)*100,"") | P13: =IFERROR(J$12/J13,"") | Q13: =IFERROR(M$12/M13,"") | R13: =IF(F13="","",IF(AND(F13>=$B$7,J13<=$B$8,M13<=$B$9),"PASS","FAIL"))
A14: quant_4bit | B14: 3d0f40a4 | C14: quantized | D14: Baseline weights quantized post-training to 4-bit NF4 (bitsandbytes), FP16 compute | E14: =IF($B14="","",COUNTIFS(Runs!$A$2:$A$21,$B14)) | F14: =IFERROR(AVERAGEIFS(Runs!$I$2:$I$21,Runs!$A$2:$A$21,$B14),"") | G14: =IFERROR(AVERAGEIFS(Runs!$J$2:$J$21,Runs!$A$2:$A$21,$B14),"") | H14: =IFERROR(AVERAGEIFS(Runs!$K$2:$K$21,Runs!$A$2:$A$21,$B14),"") | I14: =IFERROR(AVERAGEIFS(Runs!$L$2:$L$21,Runs!$A$2:$A$21,$B14),"") | J14: =IFERROR(AVERAGEIFS(Runs!$M$2:$M$21,Runs!$A$2:$A$21,$B14),"") | K14: =IFERROR(IF(E14="","",_xlfn.MAXIFS(Runs!$L$2:$L$21,Runs!$A$2:$A$21,$B14)-_xlfn.MINIFS(Runs!$L$2:$L$21,Runs!$A$2:$A$21,$B14)),"") | L14: =IFERROR(AVERAGEIFS(Runs!$Q$2:$Q$21,Runs!$A$2:$A$21,$B14),"") | M14: =IFERROR(AVERAGEIFS(Runs!$U$2:$U$21,Runs!$A$2:$A$21,$B14),"") | N14: =IFERROR(AVERAGEIFS(Runs!$S$2:$S$21,Runs!$A$2:$A$21,$B14),"") | O14: =IFERROR((F14-F$12)*100,"") | P14: =IFERROR(J$12/J14,"") | Q14: =IFERROR(M$12/M14,"") | R14: =IF(F14="","",IF(AND(F14>=$B$7,J14<=$B$8,M14<=$B$9),"PASS","FAIL"))
A15: distilled_student | B15: 6c3d1f09 | C15: distilled | D15: Distilled student: 2-layer, d=128 transformer trained on baseline's soft labels, FP32 | E15: =IF($B15="","",COUNTIFS(Runs!$A$2:$A$21,$B15)) | F15: =IFERROR(AVERAGEIFS(Runs!$I$2:$I$21,Runs!$A$2:$A$21,$B15),"") | G15: =IFERROR(AVERAGEIFS(Runs!$J$2:$J$21,Runs!$A$2:$A$21,$B15),"") | H15: =IFERROR(AVERAGEIFS(Runs!$K$2:$K$21,Runs!$A$2:$A$21,$B15),"") | I15: =IFERROR(AVERAGEIFS(Runs!$L$2:$L$21,Runs!$A$2:$A$21,$B15),"") | J15: =IFERROR(AVERAGEIFS(Runs!$M$2:$M$21,Runs!$A$2:$A$21,$B15),"") | K15: =IFERROR(IF(E15="","",_xlfn.MAXIFS(Runs!$L$2:$L$21,Runs!$A$2:$A$21,$B15)-_xlfn.MINIFS(Runs!$L$2:$L$21,Runs!$A$2:$A$21,$B15)),"") | L15: =IFERROR(AVERAGEIFS(Runs!$Q$2:$Q$21,Runs!$A$2:$A$21,$B15),"") | M15: =IFERROR(AVERAGEIFS(Runs!$U$2:$U$21,Runs!$A$2:$A$21,$B15),"") | N15: =IFERROR(AVERAGEIFS(Runs!$S$2:$S$21,Runs!$A$2:$A$21,$B15),"") | O15: =IFERROR((F15-F$12)*100,"") | P15: =IFERROR(J$12/J15,"") | Q15: =IFERROR(M$12/M15,"") | R15: =IF(F15="","",IF(AND(F15>=$B$7,J15<=$B$8,M15<=$B$9),"PASS","FAIL"))
A17: Accuracy = 16-class test accuracy (1,600 unseen-customer documents + 893 SLURP notes). Latency = one request at a time, host->GPU->host, synchronized. Shipped size = serialized weights as loaded (4-bit packs two weights per byte).

Sheet Runs
A1: run_id | B1: timestamp_utc | C1: config | D1: variant_type | E1: description | F1: trial | G1: seed | H1: n_requests | I1: accuracy | J1: acc_synthetic_docs | K1: acc_slurp_notes | L1: p50_ms | M1: p95_ms | N1: mean_ms | O1: p50_docs_ms | P1: p50_notes_ms | Q1: peak_mem_mb | R1: weights_mem_mb | S1: params_total | T1: params_non_embedding | U1: checkpoint_mb | V1: precision | W1: device | X1: torch_version | Y1: cuda_version | Z1: python_version
A2: eecf0fdd | B2: 2026-10-10T16:03:37+00:00 | C2: baseline | D2: baseline | E2: 4-layer softmax-attention transformer, FP32 | F2: 0 | G2: 627 | H2: 2493 | I2: 0.88127 | J2: 0.96375 | K2: 0.73348 | L2: 2.4854 | M2: 3.9692 | N2: 2.7712 | O2: 2.5356 | P2: 2.4187 | Q2: 29.78 | R2: 13.32 | S2: 3491856 | T2: 3163664 | U2: 13.34 | V2: fp32 | W2: Tesla T4 | X2: 2.11.0+cu130 | Y2: 13.0 | Z2: 3.13.15
A3: eecf0fdd | B3: 2026-10-10T16:03:44+00:00 | C3: baseline | D3: baseline | E3: 4-layer softmax-attention transformer, FP32 | F3: 1 | G3: 627 | H3: 2493 | I3: 0.88127 | J3: 0.96375 | K3: 0.73348 | L3: 2.3955 | M3: 3.7159 | N3: 2.6194 | O3: 2.4146 | P3: 2.3462 | Q3: 29.78 | R3: 13.32 | S3: 3491856 | T3: 3163664 | U3: 13.34 | V3: fp32 | W3: Tesla T4 | X3: 2.11.0+cu130 | Y3: 13.0 | Z3: 3.13.15
A4: eecf0fdd | B4: 2026-10-10T16:03:51+00:00 | C4: baseline | D4: baseline | E4: 4-layer softmax-attention transformer, FP32 | F4: 2 | G4: 627 | H4: 2493 | I4: 0.88127 | J4: 0.96375 | K4: 0.73348 | L4: 2.3081 | M4: 3.481 | N4: 2.4321 | O4: 2.3334 | P4: 2.2748 | Q4: 29.78 | R4: 13.32 | S4: 3491856 | T4: 3163664 | U4: 13.34 | V4: fp32 | W4: Tesla T4 | X4: 2.11.0+cu130 | Y4: 13.0 | Z4: 3.13.15
A5: eecf0fdd | B5: 2026-10-10T16:03:58+00:00 | C5: baseline | D5: baseline | E5: 4-layer softmax-attention transformer, FP32 | F5: 3 | G5: 627 | H5: 2493 | I5: 0.88127 | J5: 0.96375 | K5: 0.73348 | L5: 2.4873 | M5: 3.9202 | N5: 2.7185 | O5: 2.5137 | P5: 2.4314 | Q5: 29.78 | R5: 13.32 | S5: 3491856 | T5: 3163664 | U5: 13.34 | V5: fp32 | W5: Tesla T4 | X5: 2.11.0+cu130 | Y5: 13.0 | Z5: 3.13.15
A6: eecf0fdd | B6: 2026-10-10T16:04:04+00:00 | C6: baseline | D6: baseline | E6: 4-layer softmax-attention transformer, FP32 | F6: 4 | G6: 627 | H6: 2493 | I6: 0.88127 | J6: 0.96375 | K6: 0.73348 | L6: 2.3651 | M6: 2.9586 | N6: 2.4339 | O6: 2.3805 | P6: 2.3278 | Q6: 29.78 | R6: 13.32 | S6: 3491856 | T6: 3163664 | U6: 13.34 | V6: fp32 | W6: Tesla T4 | X6: 2.11.0+cu130 | Y6: 13.0 | Z6: 3.13.15
A7: 1610f4f4 | B7: 2026-10-10T16:07:43+00:00 | C7: linear_attention | D7: architecture | E7: Architecture variant: same 4-layer model, linear (elu+1) attention, FP32 | F7: 0 | G7: 627 | H7: 2493 | I7: 0.87124 | J7: 0.965 | K7: 0.70325 | L7: 3.9761 | M7: 6.0831 | N7: 4.2867 | O7: 4.0554 | P7: 3.847 | Q7: 29.78 | R7: 13.32 | S7: 3491856 | T7: 3163664 | U7: 13.34 | V7: fp32 | W7: Tesla T4 | X7: 2.11.0+cu130 | Y7: 13.0 | Z7: 3.13.15
A8: 1610f4f4 | B8: 2026-10-10T16:07:54+00:00 | C8: linear_attention | D8: architecture | E8: Architecture variant: same 4-layer model, linear (elu+1) attention, FP32 | F8: 1 | G8: 627 | H8: 2493 | I8: 0.87124 | J8: 0.965 | K8: 0.70325 | L8: 3.9022 | M8: 5.8875 | N8: 4.1964 | O8: 3.9273 | P8: 3.8549 | Q8: 29.78 | R8: 13.32 | S8: 3491856 | T8: 3163664 | U8: 13.34 | V8: fp32 | W8: Tesla T4 | X8: 2.11.0+cu130 | Y8: 13.0 | Z8: 3.13.15
A9: 1610f4f4 | B9: 2026-10-10T16:08:04+00:00 | C9: linear_attention | D9: architecture | E9: Architecture variant: same 4-layer model, linear (elu+1) attention, FP32 | F9: 2 | G9: 627 | H9: 2493 | I9: 0.87124 | J9: 0.965 | K9: 0.70325 | L9: 3.7975 | M9: 5.3219 | N9: 3.9837 | O9: 3.8146 | P9: 3.7572 | Q9: 29.78 | R9: 13.32 | S9: 3491856 | T9: 3163664 | U9: 13.34 | V9: fp32 | W9: Tesla T4 | X9: 2.11.0+cu130 | Y9: 13.0 | Z9: 3.13.15
A10: 1610f4f4 | B10: 2026-10-10T16:08:15+00:00 | C10: linear_attention | D10: architecture | E10: Architecture variant: same 4-layer model, linear (elu+1) attention, FP32 | F10: 3 | G10: 627 | H10: 2493 | I10: 0.87124 | J10: 0.965 | K10: 0.70325 | L10: 3.8251 | M10: 5.8073 | N10: 4.1275 | O10: 3.8505 | P10: 3.7909 | Q10: 29.78 | R10: 13.32 | S10: 3491856 | T10: 3163664 | U10: 13.34 | V10: fp32 | W10: Tesla T4 | X10: 2.11.0+cu130 | Y10: 13.0 | Z10: 3.13.15
A11: 1610f4f4 | B11: 2026-10-10T16:08:26+00:00 | C11: linear_attention | D11: architecture | E11: Architecture variant: same 4-layer model, linear (elu+1) attention, FP32 | F11: 4 | G11: 627 | H11: 2493 | I11: 0.87124 | J11: 0.965 | K11: 0.70325 | L11: 3.8575 | M11: 6.0758 | N11: 4.1994 | O11: 3.8778 | P11: 3.8081 | Q11: 29.78 | R11: 13.32 | S11: 3491856 | T11: 3163664 | U11: 13.34 | V11: fp32 | W11: Tesla T4 | X11: 2.11.0+cu130 | Y11: 13.0 | Z11: 3.13.15
A12: 3d0f40a4 | B12: 2026-10-10T16:08:46+00:00 | C12: quant_4bit | D12: quantized | E12: Baseline weights quantized post-training to 4-bit NF4 (bitsandbytes), FP16 compute | F12: 0 | G12: 627 | H12: 2493 | I12: 0.88127 | J12: 0.9625 | K12: 0.73572 | L12: 5.0262 | M12: 7.3483 | N12: 5.2132 | O12: 5.1952 | P12: 4.1314 | Q12: 19.35 | R12: 2.91 | S12: 3491856 | T12: 3163664 | U12: 2.93 | V12: nf4 weights / fp16 compute | W12: Tesla T4 | X12: 2.11.0+cu130 | Y12: 13.0 | Z12: 3.13.15
A13: 3d0f40a4 | B13: 2026-10-10T16:09:00+00:00 | C13: quant_4bit | D13: quantized | E13: Baseline weights quantized post-training to 4-bit NF4 (bitsandbytes), FP16 compute | F13: 1 | G13: 627 | H13: 2493 | I13: 0.88127 | J13: 0.9625 | K13: 0.73572 | L13: 5.1814 | M13: 7.5384 | N13: 5.3678 | O13: 5.4009 | P13: 4.3548 | Q13: 19.35 | R13: 2.91 | S13: 3491856 | T13: 3163664 | U13: 2.93 | V13: nf4 weights / fp16 compute | W13: Tesla T4 | X13: 2.11.0+cu130 | Y13: 13.0 | Z13: 3.13.15
... A21: 6c3d1f09 | B21: 2026-10-10T16:12:53+00:00 | C21: distilled_student | D21: distilled | E21: Distilled student: 2-layer, d=128 transformer trained on baseline's soft labels, FP32 | F21: 4 | G21: 627 | H21: 2493 | I21: 0.87846 | J21: 0.96312 | K21: 0.72676 | L21: 1.5728 | M21: 2.3514 | N21: 1.6603 | O21: 1.5832 | P21: 1.554 | Q21: 14.95 | R21: 2.15 | S21: 562960 | T21: 398864 | U21: 2.16 | V21: fp32 | W21: Tesla T4 | X21: 2.11.0+cu130 | Y21: 13.0 | Z21: 3.13.15

Sheet Training
A1: config | B1: variant_type | C1: teacher | D1: params_total | E1: params_non_embedding | F1: train_tokens | G1: epochs | H1: train_examples_per_epoch | I1: best_val_acc | J1: train_time_s | K1: device
A2: baseline | B2: baseline | D2: 3491856 | E2: 3163664 | F2: 16040640 | G2: 8 | H2: 11426 | I2: 0.89783282 | J2: 167.7 | K2: Tesla T4
A3: linear_attention | B3: architecture | D3: 3491856 | E3: 3163664 | F3: 16040640 | G3: 8 | H3: 11426 | I3: 0.86315789 | J3: 201.1 | K3: Tesla T4
A4: quant_4bit | B4: quantized | K4: post-training transform of baseline - no training run
A5: distilled_student | B5: distilled | C5: baseline | D5: 562960 | E5: 398864 | F5: 24060960 | G5: 12 | H5: 11426 | I5: 0.89721362 | J5: 161.7 | K5: Tesla T4
A7: train_tokens = real (non-padding) bytes the model processed over all epochs: the D in 6ND. The distilled student also ran the teacher forward on every batch (~2*N_teacher*D extra FLOPs), which is not included in its own 6ND.

Sheet Scaling
A1: Scaling-law compute estimate: what would a 10x larger model cost?
A2: Training FLOPs ~= 6 x N (parameters) x D (training tokens). Chinchilla compute-optimal budget: D ~= 20 tokens per parameter (Hoffmann et al., 2022).
A4: Inputs
A5: Baseline parameters N | B5: =INDEX(Training!$D:$D,MATCH("baseline",Training!$A:$A,0))
A6: Baseline training tokens D (as trained) | B6: =INDEX(Training!$F:$F,MATCH("baseline",Training!$A:$A,0))
A7: Unique training tokens per epoch | B7: =INDEX(Training!$F:$F,MATCH("baseline",Training!$A:$A,0))/INDEX(Training!$G:$G,MATCH("baseline",Training!$A:$A,0))
A8: Scale factor | B8: 10
A9: Chinchilla tokens per parameter | B9: 20
A10: T4 peak dense FP16 (TFLOPS) | B10: 65
A11: A100 peak dense BF16 (TFLOPS) | B11: 312
A12: Model FLOPs utilization (MFU) | B12: 0.3
A13: T4 price ($/GPU-hour) | B13: 0.35
A14: A100 price ($/GPU-hour) | B14: 1.5
A15: Mean tokens per request (test set) | B15: 163.1
A17: Projection | B17: Baseline (as trained) | C17: Baseline, Chinchilla-optimal | D17: 10x params, same data | E17: 10x params, Chinchilla-optimal
A18: Parameters N | B18: =$B$5 | C18: =$B$5 | D18: =$B$5*$B$8 | E18: =$B$5*$B$8
A19: Training tokens D | B19: =$B$6 | C19: =$B$9*C18 | D19: =$B$6 | E19: =$B$9*E18
A20: Tokens per parameter (D/N) | B20: =B19/B18 | C20: =C19/C18 | D20: =D19/D18 | E20: =E19/E18
A21: Training FLOPs (6ND) | B21: =6*B18*B19 | C21: =6*C18*C19 | D21: =6*D18*D19 | E21: =6*E18*E19
A22: Passes over our current unique data | B22: =B19/$B$7 | C22: =C19/$B$7 | D22: =D19/$B$7 | E22: =E19/$B$7
A23: T4 GPU-hours at MFU | B23: =B21/($B$10*1E12*$B$12)/3600 | C23: =C21/($B$10*1E12*$B$12)/3600 | D23: =D21/($B$10*1E12*$B$12)/3600 | E23: =E21/($B$10*1E12*$B$12)/3600
A24: T4 cost ($) | B24: =B23*$B$13 | C24: =C23*$B$13 | D24: =D23*$B$13 | E24: =E23*$B$13
A25: A100 GPU-hours at MFU | B25: =B21/($B$11*1E12*$B$12)/3600 | C25: =C21/($B$11*1E12*$B$12)/3600 | D25: =D21/($B$11*1E12*$B$12)/3600 | E25: =E21/($B$11*1E12*$B$12)/3600
A26: A100 cost ($) | B26: =B25*$B$14 | C26: =C25*$B$14 | D26: =D25*$B$14 | E26: =E25*$B$14
A27: Weights at FP32 (MB) | B27: =B18*4/2^20 | C27: =C18*4/2^20 | D27: =D18*4/2^20 | E27: =E18*4/2^20
A28: Weights at 4-bit (MB) | B28: =B18*0.5/2^20 | C28: =C18*0.5/2^20 | D28: =D18*0.5/2^20 | E28: =E18*0.5/2^20
A29: Inference GFLOPs per request (~2N per token) | B29: =2*B18*$B$15/1E9 | C29: =2*C18*$B$15/1E9 | D29: =2*D18*$B$15/1E9 | E29: =2*E18*$B$15/1E9
A31: Headline for the board
A32: ="A "&TEXT($B$8,"0")&"x model ("&TEXT(E18,"#,##0")&" params) trained compute-optimally needs "&TEXT(E19,"#,##0")&" tokens = "&TEXT(E21,"0.0E+00")&" FLOPs, about "&TEXT(E23,"#,##0.0")&" T4-hours ($"&TEXT(E24,"#,##0")&"). That is "&TEXT(E22,"#,##0")&" passes over the data we have today, so new labeled data, not GPU time, is the binding cost."
A36: Notes: 6ND counts forward + backward matmul FLOPs and ignores attention's sequence-length term (small at our ~150-token mean). 2N per token similarly understates inference cost for long documents. Chinchilla's 20 tokens/param was fit on large language models; it is used here as the standard rule of thumb, not a law for 3M-parameter classifiers.

Sheet Recommendation
A1: Ranked recommendation and residual risks
A2: Fill in after the Colab run. Rank 1 is the configuration to ship; ranks should match Board!S.
A4: Rank | B4: Config | C4: Accuracy | D4: p95 ms | E4: Shipped MB | F4: Why (one line for Sandra) | G4: Residual risks she accepts
A5: 1 | C5: =IF(B5="","",INDEX(Board!$F$12:$F$15,MATCH(B5,Board!$A$12:$A$15,0))) | D5: =IF(B5="","",INDEX(Board!$J$12:$J$15,MATCH(B5,Board!$A$12:$A$15,0))) | E5: =IF(B5="","",INDEX(Board!$M$12:$M$15,MATCH(B5,Board!$A$12:$A$15,0)))
A6: 2 | C6: =IF(B6="","",INDEX(Board!$F$12:$F$15,MATCH(B6,Board!$A$12:$A$15,0))) | D6: =IF(B6="","",INDEX(Board!$J$12:$J$15,MATCH(B6,Board!$A$12:$A$15,0))) | E6: =IF(B6="","",INDEX(Board!$M$12:$M$15,MATCH(B6,Board!$A$12:$A$15,0)))
A7: 3 | C7: =IF(B7="","",INDEX(Board!$F$12:$F$15,MATCH(B7,Board!$A$12:$A$15,0))) | D7: =IF(B7="","",INDEX(Board!$J$12:$J$15,MATCH(B7,Board!$A$12:$A$15,0))) | E7: =IF(B7="","",INDEX(Board!$M$12:$M$15,MATCH(B7,Board!$A$12:$A$15,0)))
A8: 4 | C8: =IF(B8="","",INDEX(Board!$F$12:$F$15,MATCH(B8,Board!$A$12:$A$15,0))) | D8: =IF(B8="","",INDEX(Board!$J$12:$J$15,MATCH(B8,Board!$A$12:$A$15,0))) | E8: =IF(B8="","",INDEX(Board!$M$12:$M$15,MATCH(B8,Board!$A$12:$A$15,0)))
A11: Residual-risk register (draft - edit, re-score, or delete rows)
A12: # | B12: Risk | C12: Applies to | D12: Likelihood | E12: Impact | F12: Mitigation
A13: 1 | B13: Latency was measured on a Colab T4 GPU, not the in-cab Android tablet. Absolute ms will be higher, and the ranking can change (4-bit and linear-attention kernels are tuned for GPUs). | C13: all | D13: High | E13: Medium | F13: On-device pilot on the target tablet (ONNX Runtime / ExecuTorch) before fleet rollout.
A14: 2 | B14: Document accuracy comes from synthetic scans. Real bills of lading add handwriting, stamps, multi-page scans and layouts we did not simulate. | C14: all | D14: High | E14: High | F14: Label ~500 real scans from the document archive and re-run the benchmark before sign-off.
A15: 3 | B15: Driver notes are scored on clean SLURP transcripts. On-device speech-to-text errors and cab noise are not modeled, and note accuracy is already well below document accuracy. | C15: all | D15: High | E15: Medium | F15: Benchmark against real ASR output; keep a driver confirm/correct step in the app.
A16: 4 | B16: 4-bit here uses bitsandbytes NF4, which is CUDA-only. The tablet needs a different int4 runtime whose accuracy and speed have not been measured. | C16: quant_4bit | D16: Medium | E16: Medium | F16: Re-quantize with the tablet's runtime and re-check accuracy on this test set.
A17: 5 | B17: Every model was trained once with one seed; training-run variance is not measured (only inference trials are repeated). | C17: all | D17: Medium | E17: Low | F17: Retrain the shortlisted config with 3 seeds.
A18: 6 | B18: No reject option: a document type outside the 8 classes is forced into one of them. | C18: all | D18: Medium | E18: Medium | F18: Add a confidence threshold that routes low-confidence scans to manual review.

Sheet Protocol
A1: Measurement protocol
A2: Identical for every configuration (scripts/benchmark.py).
A4: Hardware | B4: =IF(COUNTA(Runs!$A:$A)<2,"(no runs yet)",INDEX(Runs!$W:$W,2))
A5: Software | B5: =IF(COUNTA(Runs!$A:$A)<2,"(no runs yet)","torch "&INDEX(Runs!$X:$X,2)&", CUDA "&INDEX(Runs!$Y:$Y,2)&", Python "&INDEX(Runs!$Z:$Z,2))
A6: Seeds | B6: Fixed seed 627 for data generation, training, and request order (trial k uses seed 627+k).
A7: Request shape | B7: Batch size 1: one scanned document or one spoken note per request, as on the tablet.
A8: Latency | B8: Host tensor -> GPU -> forward -> argmax back on host, bracketed by torch.cuda.synchronize(); p50 / p95 over every request in a trial.
A9: Warm-up | B9: 50 untimed requests before every trial (CUDA context, kernel selection, caches).
A10: Repeated trials | B10: 5 full passes over the test set per configuration; Board shows the mean across trials and the p50 spread.
A11: Peak memory | B11: torch.cuda.max_memory_allocated() during the timed trial (weights + activations).
A12: Shipped size | B12: Serialized state_dict size as loaded; 4-bit stores packed NF4 weights + scales.
A13: Accuracy | B13: From the same timed pass, so accuracy and latency describe the same predictions.
A14: Precision | B14: Baseline, linear attention and student run FP32; 4-bit runs NF4 weights with FP16 matmuls.
A16: Evaluation set
A17: Split | B17: Source | C17: Examples | D17: Mean bytes | E17: p95 bytes
A18: train | B18: slurp_notes | C18: 3426 | D18: 38.6 | E18: 69
A19: train | B19: synthetic_docs | C19: 8000 | D19: 232.7 | E19: 458
A20: val | B20: slurp_notes | C20: 615 | D20: 38.5 | E20: 69
A21: val | B21: synthetic_docs | C21: 1000 | D21: 236.6 | E21: 468
A22: test | B22: slurp_notes | C22: 893 | D22: 38.6 | E22: 71
A23: test | B23: synthetic_docs | C23: 1600 | D23: 231 | E23: 458
A25: synthetic_docs: scripts/generate_documents.py, 8 freight document types with OCR noise, cut-off headers and partial photos; the test split uses unseen company/city names. slurp_notes: SLURP transcripts (github.com/pswietojanski/slurp, CC BY 4.0), 8 in-cab intents, SLURP's own splits.
